{"the":7,"he ":6,"e s":1," su":1,"sun":1,"un ":1,"n w":1," wa":1,"was":1,"as ":1,"s s":1," se":2,"set":1,"ett":1,"tti":1,"tin":1,"ing":4,"ng ":3,"g o":1," ov":1,"ove":1,"ver":2,"er ":1,"r t":1," th":7,"e q":1," qu":2,"qui":1,"uie":1,"iet":1,"et ":1,"t h":1," hi":1,"hil":1,"ill":3,"lls":1,"ls.":1,"s. ":2,". a":1," a ":1,"a s":1," so":2,"sof":1,"oft":1,"ft ":1,"t b":1," br":1,"bre":1,"ree":2,"eez":1,"eze":1,"ze ":1,"e r":1," ru":1,"rus":3,"ust":1,"stl":1,"tle":1,"led":1,"ed ":4,"d t":1,"e t":2," tr":1,"tre":1,"ees":1,"es,":1,"s, ":2,", w":1," wh":1,"whi":1,"his":1,"isp":1,"spe":1,"per":1,"eri":1,"rin":2,"g s":1,"sec":1,"ecr":1,"cre":1,"ret":1,"ets":1,"ts ":2,"s o":1," of":3,"of ":3,"f t":1,"e d":1," da":1,"day":2,"ay.":1,"y. ":2,". c":1," cy":2,"cyr":2,"yru":2,"us ":2,"s l":3," lo":1,"loo":1,"ook":1,"oke":1,"ked":1,"d u":1," up":1,"up,":1,"p, ":1,", e":1," ey":1,"eye":1,"yes":1,"es ":1,"s f":1," fu":2,"ful":2,"ull":2,"ll ":4,"l o":2,"f q":1,"que":1,"ues":1,"est":1,"sti":1,"tio":1,"ion":1,"ons":1,"ns,":1,", h":1," he":1,"hea":1,"ear":2,"art":1,"rt ":1,"t f":1,"f w":1," wo":4,"won":1,"ond":1,"nde":1,"der":1,"er.":1,"r.\n":1,".\n\n":4,"\n\n\"":1,"\n\"w":1,"\"wh":2,"wha":2,"hat":2,"at ":2,"t w":1," wi":3,"wil":2,"l w":1," we":1,"we ":1,"e l":1," le":1,"lea":1,"arn":1,"rn ":1,"n t":1," to":1,"tod":1,"oda":1,"ay?":1,"y?\"":1,"?\" ":1,"\" i":1," it":2,"it ":1,"t t":3,"tho":2,"hou":2,"oug":2,"ugh":2,"ght":2,"ht.":2,"t. ":1,". \"":1," \"w":1,"t p":1," pa":1,"pat":2,"att":2,"tte":2,"ter":2,"ern":2,"rns":2,"ns ":2,"s w":1,"l r":1," re":2,"rev":1,"eve":2,"vea":1,"eal":1,"al ":1,"l t":1,"hem":1,"ems":1,"mse":1,"sel":1,"elv":1,"lve":1,"ves":1,"es?":1,"s?\"":1,"?\"\n":1,"\"\n\n":1,"\n\nt":1,"\nth":1,"e w":3,"win":1,"ind":1,"nd ":2,"d d":1," di":1,"did":1,"id ":1,"d n":1," no":1,"not":1,"ot ":1,"t a":1," an":1,"ans":1,"nsw":1,"swe":1,"wer":1,"er,":1,"r, ":1,", b":1," bu":1,"but":1,"ut ":1,"wor":3,"orl":1,"rld":1,"ld ":1,"d k":1," ke":1,"kep":1,"ept":1,"pt ":1," tu":1,"tur":1,"urn":1,"rni":1,"nin":1,"ng.":1,"g.\n":1,"\n\np":1,"\npa":1,"s b":2," be":3,"bec":3,"eca":3,"cam":3,"ame":3,"me ":3,"ord":2,"rds":2,"ds.":1,". w":1,"ds ":1,"e m":1," me":2,"mem":2,"emo":2,"mor":2,"ory":2,"ry.":1,". m":1,"ry ":2,"y b":1,"t.\n":1,"\n\na":1,"\nan":1,"and":1,"d c":1," li":1,"lis":1,"ist":1,"ste":1,"ten":1,"ene":1,"ned":1,"ed,":1,"d, ":1,", s":1," st":1,"sto":1,"tor":1,"ori":1,"g e":1," ev":1,"ery":1,"y r":1,"rep":1,"epe":1,"pea":1,"eat":1,"ate":1,"ted":1,"d e":1," ec":1,"ech":1,"cho":1,"ho ":1,"o i":1," in":1,"in ":1,"n i":1,"its":1," la":1,"lay":1,"aye":1,"yer":1,"ere":1,"red":1,"d s":1,"sou":1,"oul":1,"ul.":1,"l.\n":1}